simple_keyword_clusterer/__init__.py
simple_keyword_clusterer/blacklist.txt
simple_keyword_clusterer/clustering.py
simple_keyword_clusterer/preprocessing.py
simple_keyword_clusterer/simple_keyword_clusterer.py
simple_keyword_clusterer/to_normalize.txt
simple_keyword_clusterer-1.3.dist-info/LICENSE.txt
simple_keyword_clusterer-1.3.dist-info/METADATA
simple_keyword_clusterer-1.3.dist-info/WHEEL
simple_keyword_clusterer-1.3.dist-info/top_level.txt
simple_keyword_clusterer-1.3.dist-info/RECORD
