Metadata-Version: 2.1
Name: simple-keyword-clusterer
Version: 1.3
Summary: Extract higher level clusters from keywords
Home-page: https://github.com/andrea-dagostino/simple_keyword_clusterer
Author: Andrea D'Agostino
Author-email: andrea@andreadagostino.com
License: MIT
Keywords: keyword-extraction,keyword-clustering
Platform: UNKNOWN
Classifier: Programming Language :: Python :: 3
Classifier: License :: OSI Approved :: MIT License
Classifier: Operating System :: OS Independent
Requires-Python: >=3.6
Requires-Dist: scikit-learn
Requires-Dist: tqdm
Requires-Dist: seaborn
Requires-Dist: numpy
Requires-Dist: nltk
Requires-Dist: matplotlib
Requires-Dist: pandas
